{
  "_id": "bNjpiEQhK8nDSqXx",
  "_key": "!items!bNjpiEQhK8nDSqXx",
  "name": "Tinder Box",
  "type": "item",
  "img": "modules/coc7-cthulhu-invictus/assets/icons/equipment/default.webp",
  "system": {
    "description": {
      "value": "<p>Box of flammable bundles for quick fire-starting</p>",
      "keeper": ""
    },
    "cost": {
      "value": 3,
      "unit": "sestertii"
    },
    "properties": {}
  },
  "effects": [],
  "folder": null,
  "sort": 3000,
  "flags": {
    "coc7-cthulhu-invictus": {}
  },
  "ownership": {
    "default": 0
  },
  "_stats": {
    "compendiumSource": null,
    "duplicateSource": null,
    "coreVersion": "13",
    "systemId": "CoC7",
    "systemVersion": "0.10.0",
    "createdTime": null,
    "modifiedTime": null,
    "lastModifiedBy": null
  }
}
